Metadata-Version: 2.0
Name: odoo10-addon-cms-status-message-example
Version: 10.0.1.0.0
Summary: Example module on what you can do with cms_status_message
Home-page: https://github.com/OCA/website-cms
Author: Camptocamp,Odoo Community Association (OCA)
Author-email: support@odoo-community.org
License: AGPL-3
Platform: UNKNOWN
Classifier: Programming Language :: Python :: 2.7
Classifier: Framework :: Odoo
Classifier: License :: OSI Approved :: GNU Affero General Public License v3
Requires-Dist: odoo (<10.1dev,>=10.0)
